README.md
setup.py
gitlab/__init__.py
gitlab.egg-info/PKG-INFO
gitlab.egg-info/SOURCES.txt
gitlab.egg-info/dependency_links.txt
gitlab.egg-info/top_level.txt